{"1":{"page_content":"","ref_size":{"width":1190,"height":1684}},"2":{"page_content":"","ref_size":{"width":1190,"height":1684}},"3":{"page_content":"","ref_size":{"width":1190,"height":1684}},"4":{"page_content":"","ref_size":{"width":1190,"height":1684}},"5":{"page_content":"","ref_size":{"width":1190,"height":1684}},"6":{"page_content":"","ref_size":{"width":1190,"height":1684}},"7":{"page_content":"","ref_size":{"width":1190,"height":1684}},"8":{"page_content":"","ref_size":{"width":1190,"height":1684}},"9":{"page_content":"","ref_size":{"width":1190,"height":1684}}}